{"cameraMode":{"drawMode":0,"name":"Shaded","section":"Shading Mode"},"sceneLighting":true,"audioPlay":false,"sceneViewState":{"m_AlwaysRefresh":false,"showFog":true,"showSkybox":true,"showFlares":true,"showImageEffects":true,"showParticleSystems":true,"showVisualEffectGraphs":true,"m_FxEnabled":true},"in2DMode":false,"pivot":{"x":-0.9855823516845703,"y":2.1400246620178224,"z":1.0516295433044434},"rotation":{"x":0.15514130890369416,"y":0.08170820027589798,"z":-0.012875407002866269,"w":0.9844310283660889},"size":6.31949520111084,"orthographic":false}